{
  "annotations": {"list": []},
  "editable": false,
  "graphTooltip": 1,
  "panels": [
    {
      "datasource": {"type": "prometheus", "uid": "fraudcell-prometheus"},
      "fieldConfig": {"defaults": {"unit": "reqps"}, "overrides": []},
      "gridPos": {"h": 8, "w": 12, "x": 0, "y": 0},
      "id": 1,
      "options": {"legend": {"displayMode": "table", "placement": "bottom"}},
      "targets": [{"expr": "sum by (job) (rate(http_server_requests_seconds_count[5m]))", "refId": "A"}],
      "title": "HTTP istek hızı",
      "type": "timeseries"
    },
    {
      "datasource": {"type": "prometheus", "uid": "fraudcell-prometheus"},
      "fieldConfig": {"defaults": {"unit": "percentunit"}, "overrides": []},
      "gridPos": {"h": 8, "w": 12, "x": 12, "y": 0},
      "id": 2,
      "options": {"legend": {"displayMode": "table", "placement": "bottom"}},
      "targets": [{"expr": "sum by (job) (rate(http_server_requests_seconds_count{status=~\"5..\"}[5m])) / clamp_min(sum by (job) (rate(http_server_requests_seconds_count[5m])), 0.001)", "refId": "A"}],
      "title": "5xx oranı",
      "type": "timeseries"
    }
  ],
  "refresh": "15s",
  "schemaVersion": 41,
  "tags": ["fraudcell"],
  "templating": {"list": []},
  "time": {"from": "now-1h", "to": "now"},
  "timezone": "Europe/Istanbul",
  "title": "FraudCell Genel Bakış",
  "uid": "fraudcell-overview",
  "version": 1
}

